makemkv/__init__.py
makemkv/__main__.py
makemkv/_cli_params.py
makemkv/makemkv.py
makemkv/output_codes.py
makemkv/progress.py
makemkv/py.typed
makemkv/types.py
makemkv-0.3.1.dist-info/entry_points.txt
makemkv-0.3.1.dist-info/LICENSE
makemkv-0.3.1.dist-info/WHEEL
makemkv-0.3.1.dist-info/METADATA
makemkv-0.3.1.dist-info/RECORD
