Metadata-Version: 2.1
Name: makemkv
Version: 0.3.1
Summary: Python wrapper for MakeMKV
Keywords: mkv,dvd,bluray,ripping,makemkv,remuxing,metadata
Author-email: d-k-bo <dkbo@mail.de>
Requires-Python: >=3.9
Classifier: Development Status :: 2 - Pre-Alpha
Classifier: License :: OSI Approved :: MIT License
Classifier: Programming Language :: Python :: 3.9
Classifier: Programming Language :: Python :: 3.10
Classifier: Topic :: Multimedia :: Video
Requires-Dist: iso639-lang >= 2.0.0
Requires-Dist: typing-extensions >= 4.0
Requires-Dist: click >= 8.0 ; extra == "cli"
Requires-Dist: rich >= 11.0 ; extra == "cli"
Requires-Dist: mkdocs ~= 1.2.3 ; extra == "docs"
Requires-Dist: mkdocstrings[python] ~= 0.18.0 ; extra == "docs"
Requires-Dist: mkdocs-material ~= 8.1.11  ; extra == "docs"
Requires-Dist: pytest>=7.1.2 ; extra == "test"
Requires-Dist: pytest-cov>=3.0.0 ; extra == "test"
Requires-Dist: trycast>=1.0.0 ; extra == "test"
Project-URL: Documentation, https://python-makemkv.readthedocs.io/en/latest/
Project-URL: Source, https://github.com/d-k-bo/python-makemkv
Provides-Extra: cli
Provides-Extra: docs
Provides-Extra: test
